{
  "id": "3eb78a64-1e75-4ef6-8e50-c4d30b15e1de",
  "title": "Lee Cronin's 'The Mummy'",
  "version": "v14",
  "director": "Lee Cronin",
  "producer": "John Keville",
  "lineProducer": "Niamh Gale",
  "productionCompany": "Wild Atlantic",
  "firstAD": "Daire Glynn",
  "secondAD": "Nicola Long",
  "scriptTitle": "Shooting Script",
  "scriptEpisode": "",
  "scriptDated": "2025-05-19",
  "scriptColor": "2nd Pink",
  "prepStartDate": "2025-01-06",
  "shootStartDate": "2025-03-24",
  "wrapDate": "2025-06-16",
  "notes": "",
  "isVersioned": true,
  "created": "2025-05-18T21:53:49.413582Z",
  "updated": "2025-05-18T21:53:49.413582Z",
  "currentWorkspaceVersion": "8f928202-a10a-4282-9ff5-df03ad6a7ba1"
}